{
    "games": [
        {
            "name": "9 Years of Shadows",
            "categories": [
                "PC",
                "Nintendo Switch"
            ],
            "windows": "",
            "linux": "",
            "macos": "",
            "other_download_links": []
        },
        {
            "name": "1-2-Switch",
            "categories": [
                "Nintendo Switch"
            ],
            "windows": "",
            "linux": "",
            "macos": "",
            "other_download_links": []
        },
        {
            "name": "Hue",
            "categories": [
                "PS Vita",
                "Nintendo Switch",
                "PC"
            ],
            "windows": "",
            "linux": "",
            "macos": "",
            "other_download_links": []
        },
        {
            "name": "Batman: Arkham Origins Blackgate",
            "categories": [
                "Nintendo 3DS"
            ],
            "windows": "",
            "linux": "",
            "macos": "",
            "other_download_links": []
        },
        {
            "name": "Rayman Origins",
            "categories": [
                "Nintendo Wii",
                "PS Vita",
                "Nintendo 3DS",
                "PC"
            ],
            "windows": "",
            "linux": "",
            "macos": "",
            "other_download_links": []
        },
        {
            "name": "Castle of Illusion",
            "categories": [
                "Android",
                "PC"
            ],
            "windows": "",
            "linux": "",
            "macos": "",
            "other_download_links": []
        },
        {
            "name": "Castlevania: Aria of Sorrow",
            "categories": [
                "GBA"
            ],
            "windows": "",
            "linux": "",
            "macos": "",
            "other_download_links": []
        },
        {
            "name": "Midnight Club: Street Racing",
            "categories": [
                "Playstation 2"
            ],
            "windows": "",
            "linux": "",
            "macos": "",
            "other_download_links": []
        },
        {
            "name": "Ico",
            "categories": [
                "Playstation 3"
            ],
            "windows": "",
            "linux": "",
            "macos": "",
            "other_download_links": []
        },
        {
            "name": "Dragon Warrior",
            "categories": [
                "NES"
            ],
            "windows": "",
            "linux": "",
            "macos": "",
            "other_download_links": []
        },
        {
            "name": "Super Mario World",
            "categories": [
                "SNES"
            ],
            "windows": "",
            "linux": "",
            "macos": "",
            "other_download_links": []
        },
        {
            "name": "Alex Kidd in Miracle World DX",
            "categories": [
                "PC"
            ],
            "windows": "",
            "linux": "",
            "macos": "",
            "other_download_links": []
        },
        {
            "name": "I Am The Hero",
            "categories": [
                "PS Vita",
                "Nintendo Switch",
                "PC"
            ],
            "windows": "",
            "linux": "",
            "macos": "",
            "other_download_links": []
        },
        {
            "name": "Captain Toad: Treasure Tracker",
            "categories": [
                "Nintendo 3DS",
                "Nintendo Switch"
            ],
            "windows": "",
            "linux": "",
            "macos": "",
            "other_download_links": []
        },
        {
            "name": "Link's Crossbow Training",
            "categories": [
                "Nintendo Wii"
            ],
            "windows": "",
            "linux": "",
            "macos": "",
            "other_download_links": []
        },
        {
            "name": "The Legend of Zelda: The Minish Cap",
            "categories": [
                "GBA"
            ],
            "windows": "",
            "linux": "",
            "macos": "",
            "other_download_links": []
        },
        {
            "name": "Rain",
            "categories": [
                "Playstation 3"
            ],
            "windows": "",
            "linux": "",
            "macos": "",
            "other_download_links": []
        },
        {
            "name": "The Legend of Zelda",
            "categories": [
                "NES"
            ],
            "windows": "",
            "linux": "",
            "macos": "",
            "other_download_links": []
        },
        {
            "name": "The Legend of Zelda: A Link to the Past",
            "categories": [
                "SNES"
            ],
            "windows": "",
            "linux": "",
            "macos": "",
            "other_download_links": []
        },
        {
            "name": "Ashen",
            "categories": [
                "PC",
                "Nintendo Switch"
            ],
            "windows": "",
            "linux": "",
            "macos": "",
            "other_download_links": []
        },
        {
            "name": "A Hole New World",
            "categories": [
                "Nintendo Switch",
                "PS Vita"
            ],
            "windows": "",
            "linux": "",
            "macos": "",
            "other_download_links": []
        },
        {
            "name": "LoZ: ALBW",
            "categories": [
                "Nintendo 3DS"
            ],
            "windows": "",
            "linux": "",
            "macos": "",
            "other_download_links": []
        },
        {
            "name": "Super Mario Bros. Wii",
            "categories": [
                "Nintendo Wii"
            ],
            "windows": "",
            "linux": "",
            "macos": "",
            "other_download_links": []
        },
        {
            "name": "Metroid Fusion",
            "categories": [
                "GBA"
            ],
            "windows": "",
            "linux": "",
            "macos": "",
            "other_download_links": []
        },
        {
            "name": "Silent Hill: Downpour",
            "categories": [
                "Playstation 3"
            ],
            "windows": "",
            "linux": "",
            "macos": "",
            "other_download_links": []
        },
        {
            "name": "Zelda II: The Adventure of Link",
            "categories": [
                "NES"
            ],
            "windows": "",
            "linux": "",
            "macos": "",
            "other_download_links": []
        },
        {
            "name": "Blasphemous",
            "categories": [
                "PC",
                "Nintendo Switch"
            ],
            "windows": "",
            "linux": "",
            "macos": "",
            "other_download_links": []
        },
        {
            "name": "Luigi's Mansion",
            "categories": [
                "Nintendo 3DS"
            ],
            "windows": "",
            "linux": "",
            "macos": "",
            "other_download_links": []
        },
        {
            "name": "Metroid: Zero Mission",
            "categories": [
                "GBA"
            ],
            "windows": "",
            "linux": "",
            "macos": "",
            "other_download_links": []
        },
        {
            "name": "Blasphemous 2",
            "categories": [
                "PC",
                "Nintendo Switch"
            ],
            "windows": "",
            "linux": "",
            "macos": "",
            "other_download_links": []
        },
        {
            "name": "Axiom Verge",
            "categories": [
                "Nintendo Switch"
            ],
            "windows": "",
            "linux": "",
            "macos": "",
            "other_download_links": []
        },
        {
            "name": "Mario Kart 7",
            "categories": [
                "Nintendo 3DS"
            ],
            "windows": "",
            "linux": "",
            "macos": "",
            "other_download_links": []
        },
        {
            "name": "Pokémon Emerald",
            "categories": [
                "GBA"
            ],
            "windows": "",
            "linux": "",
            "macos": "",
            "other_download_links": []
        },
        {
            "name": "Bloodhound",
            "categories": [
                "PC"
            ],
            "windows": "",
            "linux": "",
            "macos": "",
            "other_download_links": []
        },
        {
            "name": "Metroid: Samus Returns",
            "categories": [
                "Nintendo 3DS"
            ],
            "windows": "",
            "linux": "",
            "macos": "",
            "other_download_links": []
        },
        {
            "name": "BloodRayne",
            "categories": [
                "PC"
            ],
            "windows": "",
            "linux": "",
            "macos": "",
            "other_download_links": []
        },
        {
            "name": "Metroid: SR 3DS",
            "categories": [
                "Nintendo 3DS"
            ],
            "windows": "",
            "linux": "",
            "macos": "",
            "other_download_links": []
        },
        {
            "name": "BloodRayne 2",
            "categories": [
                "PC"
            ],
            "windows": "",
            "linux": "",
            "macos": "",
            "other_download_links": []
        },
        {
            "name": "BloodRayne: ReVamped",
            "categories": [
                "Nintendo Switch"
            ],
            "windows": "",
            "linux": "",
            "macos": "",
            "other_download_links": []
        },
        {
            "name": "New Super Mario Bros. 2",
            "categories": [
                "Nintendo 3DS"
            ],
            "windows": "",
            "linux": "",
            "macos": "",
            "other_download_links": []
        },
        {
            "name": "BloodRayne 2: Terminal Cut",
            "categories": [
                "PC"
            ],
            "windows": "",
            "linux": "",
            "macos": "",
            "other_download_links": []
        },
        {
            "name": "Bloodstained: Ritual of the Night",
            "categories": [
                "Nintendo Switch",
                "PC"
            ],
            "windows": "",
            "linux": "",
            "macos": "",
            "other_download_links": []
        },
        {
            "name": "BloodRayne Betrayal",
            "categories": [
                "PC"
            ],
            "windows": "",
            "linux": "",
            "macos": "",
            "other_download_links": []
        },
        {
            "name": "Bright Memory Infinite",
            "categories": [
                "Nintendo Switch",
                "PC"
            ],
            "windows": "",
            "linux": "",
            "macos": "",
            "other_download_links": []
        },
        {
            "name": "Resident Evil: Revelations 3DS",
            "categories": [
                "Nintendo 3DS"
            ],
            "windows": "",
            "linux": "",
            "macos": "",
            "other_download_links": []
        },
        {
            "name": "BloodRayne: Terminal Cut",
            "categories": [
                "PC"
            ],
            "windows": "",
            "linux": "",
            "macos": "",
            "other_download_links": []
        },
        {
            "name": "Resident Evil: The Mercenaries 3D",
            "categories": [
                "Nintendo 3DS"
            ],
            "windows": "",
            "linux": "",
            "macos": "",
            "other_download_links": []
        },
        {
            "name": "Carrion",
            "categories": [
                "Nintendo Switch",
                "PC"
            ],
            "windows": "",
            "linux": "",
            "macos": "",
            "other_download_links": []
        },
        {
            "name": "Steamworld Dig",
            "categories": [
                "Nintendo 3DS"
            ],
            "windows": "",
            "linux": "",
            "macos": "",
            "other_download_links": []
        },
        {
            "name": "Coffin Dodgers",
            "categories": [
                "Nintendo Switch",
                "PC"
            ],
            "windows": "",
            "linux": "",
            "macos": "",
            "other_download_links": []
        },
        {
            "name": "The Legend of Zelda: Ocarina of Time 3D",
            "categories": [
                "Nintendo 3DS"
            ],
            "windows": "",
            "linux": "",
            "macos": "",
            "other_download_links": []
        },
        {
            "name": "Brothers: A Tale of Two Sons Remake",
            "categories": [
                "PC"
            ],
            "windows": "",
            "linux": "",
            "macos": "",
            "other_download_links": []
        },
        {
            "name": "Death's Door",
            "categories": [
                "Nintendo Switch"
            ],
            "windows": "",
            "linux": "",
            "macos": "",
            "other_download_links": []
        },
        {
            "name": "The Legend of Zelda: Tri Force Heroes",
            "categories": [
                "Nintendo 3DS"
            ],
            "windows": "",
            "linux": "",
            "macos": "",
            "other_download_links": []
        },
        {
            "name": "Bully: Scholarship Edition",
            "categories": [
                "PC"
            ],
            "windows": "",
            "linux": "",
            "macos": "",
            "other_download_links": []
        },
        {
            "name": "Donkey Kong Country: Tropical Freeze",
            "categories": [
                "Nintendo Switch"
            ],
            "windows": "",
            "linux": "",
            "macos": "",
            "other_download_links": []
        },
        {
            "name": "ULTIMATE NES REMIX",
            "categories": [
                "Nintendo 3DS"
            ],
            "windows": "",
            "linux": "",
            "macos": "",
            "other_download_links": []
        },
        {
            "name": "Doom 64",
            "categories": [
                "Nintendo Switch",
                "PC"
            ],
            "windows": "",
            "linux": "",
            "macos": "",
            "other_download_links": []
        },
        {
            "name": "Yoshi's New Island",
            "categories": [
                "Nintendo 3DS"
            ],
            "windows": "",
            "linux": "",
            "macos": "",
            "other_download_links": []
        },
        {
            "name": "Ender Lilies: Quietus of the Knights",
            "categories": [
                "Nintendo Switch",
                "PC"
            ],
            "windows": "",
            "linux": "",
            "macos": "",
            "other_download_links": []
        },
        {
            "name": "Eternal Hope",
            "categories": [
                "Nintendo Switch",
                "PC"
            ],
            "windows": "",
            "linux": "",
            "macos": "",
            "other_download_links": []
        },
        {
            "name": "Dead Rising 4",
            "categories": [
                "PC"
            ],
            "windows": "",
            "linux": "",
            "macos": "",
            "other_download_links": []
        },
        {
            "name": "Evergate",
            "categories": [
                "Nintendo Switch",
                "PC"
            ],
            "windows": "",
            "linux": "",
            "macos": "",
            "other_download_links": []
        },
        {
            "name": "Dead Space 3: Awakened",
            "categories": [
                "PC"
            ],
            "windows": "",
            "linux": "",
            "macos": "",
            "other_download_links": []
        },
        {
            "name": "Fe",
            "categories": [
                "Nintendo Switch",
                "PC"
            ],
            "windows": "",
            "linux": "",
            "macos": "",
            "other_download_links": []
        },
        {
            "name": "Dolmen",
            "categories": [
                "PC"
            ],
            "windows": "",
            "linux": "",
            "macos": "",
            "other_download_links": []
        },
        {
            "name": "Fez",
            "categories": [
                "Nintendo Switch"
            ],
            "windows": "",
            "linux": "",
            "macos": "",
            "other_download_links": []
        },
        {
            "name": "Doom",
            "categories": [
                "PC"
            ],
            "windows": "",
            "linux": "",
            "macos": "",
            "other_download_links": []
        },
        {
            "name": "Final Fantasy VII",
            "categories": [
                "Nintendo Switch",
                "PC"
            ],
            "windows": "",
            "linux": "",
            "macos": "",
            "other_download_links": []
        },
        {
            "name": "Grapple Dog",
            "categories": [
                "Nintendo Switch",
                "PC"
            ],
            "windows": "",
            "linux": "",
            "macos": "",
            "other_download_links": []
        },
        {
            "name": "Graveyard Keeper",
            "categories": [
                "Nintendo Switch",
                "PC"
            ],
            "windows": "",
            "linux": "",
            "macos": "",
            "other_download_links": []
        },
        {
            "name": "ENDER MAGNOLIA: Bloom in the Mist",
            "categories": [
                "PC"
            ],
            "windows": "",
            "linux": "",
            "macos": "",
            "other_download_links": []
        },
        {
            "name": "GRIS",
            "categories": [
                "Nintendo Switch",
                "PC"
            ],
            "windows": "",
            "linux": "",
            "macos": "",
            "other_download_links": []
        },
        {
            "name": "Haiku, the Robot",
            "categories": [
                "Nintendo Switch",
                "PC"
            ],
            "windows": "",
            "linux": "",
            "macos": "",
            "other_download_links": []
        },
        {
            "name": "Hotline Miami 2: Wrong Number",
            "categories": [
                "Nintendo Switch"
            ],
            "windows": "",
            "linux": "",
            "macos": "",
            "other_download_links": []
        },
        {
            "name": "Fallout 3: GOTY",
            "categories": [
                "PC"
            ],
            "windows": "",
            "linux": "",
            "macos": "",
            "other_download_links": []
        },
        {
            "name": "It Takes Two",
            "categories": [
                "Nintendo Switch"
            ],
            "windows": "",
            "linux": "",
            "macos": "",
            "other_download_links": []
        },
        {
            "name": "Freedom Fighters",
            "categories": [
                "PC"
            ],
            "windows": "",
            "linux": "",
            "macos": "",
            "other_download_links": []
        },
        {
            "name": "Journey to the Savage Planet",
            "categories": [
                "Nintendo Switch",
                "PC"
            ],
            "windows": "",
            "linux": "",
            "macos": "",
            "other_download_links": []
        },
        {
            "name": "Ghosts 'n Goblins Resurrection",
            "categories": [
                "PC"
            ],
            "windows": "",
            "linux": "",
            "macos": "",
            "other_download_links": []
        },
        {
            "name": "Kirby and the Forgotten Land",
            "categories": [
                "Nintendo Switch"
            ],
            "windows": "",
            "linux": "",
            "macos": "",
            "other_download_links": []
        },
        {
            "name": "Kirby's Dream Buffet",
            "categories": [
                "Nintendo Switch"
            ],
            "windows": "",
            "linux": "",
            "macos": "",
            "other_download_links": []
        },
        {
            "name": "Luigi's Mansion 2 HD",
            "categories": [
                "Nintendo Switch"
            ],
            "windows": "",
            "linux": "",
            "macos": "",
            "other_download_links": []
        },
        {
            "name": "Mario vs. Donkey Kong",
            "categories": [
                "Nintendo Switch"
            ],
            "windows": "",
            "linux": "",
            "macos": "",
            "other_download_links": []
        },
        {
            "name": "GTA: Liberty City Stories",
            "categories": [
                "PC"
            ],
            "windows": "",
            "linux": "",
            "macos": "",
            "other_download_links": []
        },
        {
            "name": "Metroid Dread",
            "categories": [
                "Nintendo Switch"
            ],
            "windows": "",
            "linux": "",
            "macos": "",
            "other_download_links": []
        },
        {
            "name": "Metroid Prime Remastered",
            "categories": [
                "Nintendo Switch"
            ],
            "windows": "",
            "linux": "",
            "macos": "",
            "other_download_links": []
        },
        {
            "name": "Mortal Shell: Complete Edition",
            "categories": [
                "Nintendo Switch"
            ],
            "windows": "",
            "linux": "",
            "macos": "",
            "other_download_links": []
        },
        {
            "name": "New Super Mario Bros. U Deluxe",
            "categories": [
                "Nintendo Switch"
            ],
            "windows": "",
            "linux": "",
            "macos": "",
            "other_download_links": []
        },
        {
            "name": "Olija",
            "categories": [
                "Nintendo Switch",
                "PC"
            ],
            "windows": "",
            "linux": "",
            "macos": "",
            "other_download_links": []
        },
        {
            "name": "Katana Zero",
            "categories": [
                "PC"
            ],
            "windows": "",
            "linux": "",
            "macos": "",
            "other_download_links": []
        },
        {
            "name": "Paradise Lost",
            "categories": [
                "Nintendo Switch",
                "PC"
            ],
            "windows": "",
            "linux": "",
            "macos": "",
            "other_download_links": []
        },
        {
            "name": "Kona",
            "categories": [
                "PC"
            ],
            "windows": "",
            "linux": "",
            "macos": "",
            "other_download_links": []
        },
        {
            "name": "Police Stories",
            "categories": [
                "Nintendo Switch",
                "PC"
            ],
            "windows": "",
            "linux": "",
            "macos": "",
            "other_download_links": []
        },
        {
            "name": "Mass Effect L.E",
            "categories": [
                "PC"
            ],
            "windows": "",
            "linux": "",
            "macos": "",
            "other_download_links": []
        },
        {
            "name": "Princess Peach: Showtime!",
            "categories": [
                "Nintendo Switch"
            ],
            "windows": "",
            "linux": "",
            "macos": "",
            "other_download_links": []
        },
        {
            "name": "Nocturne",
            "categories": [
                "PC"
            ],
            "windows": "",
            "linux": "",
            "macos": "",
            "other_download_links": []
        },
        {
            "name": "Project Warlock",
            "categories": [
                "Nintendo Switch",
                "PC"
            ],
            "windows": "",
            "linux": "",
            "macos": "",
            "other_download_links": []
        },
        {
            "name": "Running on Magic",
            "categories": [
                "Nintendo Switch",
                "PC"
            ],
            "windows": "",
            "linux": "",
            "macos": "",
            "other_download_links": []
        },
        {
            "name": "PAC-MAN WORLD Re-PAC",
            "categories": [
                "PC"
            ],
            "windows": "",
            "linux": "",
            "macos": "",
            "other_download_links": []
        },
        {
            "name": "Spyro Reignited Trilogy",
            "categories": [
                "Nintendo Switch",
                "PC"
            ],
            "windows": "",
            "linux": "",
            "macos": "",
            "other_download_links": []
        },
        {
            "name": "Super Mario 3D World + Bowser’s Fury",
            "categories": [
                "Nintendo Switch"
            ],
            "windows": "",
            "linux": "",
            "macos": "",
            "other_download_links": []
        },
        {
            "name": "Super Mario Bros. Wonder",
            "categories": [
                "Nintendo Switch"
            ],
            "windows": "",
            "linux": "",
            "macos": "",
            "other_download_links": []
        },
        {
            "name": "Police Stories: The Academy",
            "categories": [
                "PC"
            ],
            "windows": "",
            "linux": "",
            "macos": "",
            "other_download_links": []
        },
        {
            "name": "T.M.N.T: Shredder's Revenge",
            "categories": [
                "Nintendo Switch",
                "PC"
            ],
            "windows": "",
            "linux": "",
            "macos": "",
            "other_download_links": []
        },
        {
            "name": "Prey",
            "categories": [
                "PC"
            ],
            "windows": "",
            "linux": "",
            "macos": "",
            "other_download_links": []
        },
        {
            "name": "Tails of Iron",
            "categories": [
                "Nintendo Switch",
                "PC"
            ],
            "windows": "",
            "linux": "",
            "macos": "",
            "other_download_links": []
        },
        {
            "name": "Prey: Mooncrash",
            "categories": [
                "PC"
            ],
            "windows": "",
            "linux": "",
            "macos": "",
            "other_download_links": []
        },
        {
            "name": "The Last Faith",
            "categories": [
                "Nintendo Switch",
                "PC"
            ],
            "windows": "",
            "linux": "",
            "macos": "",
            "other_download_links": []
        },
        {
            "name": "Touhou Luna Nights",
            "categories": [
                "Nintendo Switch"
            ],
            "windows": "",
            "linux": "",
            "macos": "",
            "other_download_links": []
        },
        {
            "name": "Zelda: Link's Awakening",
            "categories": [
                "Nintendo Switch"
            ],
            "windows": "",
            "linux": "",
            "macos": "",
            "other_download_links": []
        },
        {
            "name": "Resident Evil 3",
            "categories": [
                "PC"
            ],
            "windows": "",
            "linux": "",
            "macos": "",
            "other_download_links": []
        },
        {
            "name": "Roki",
            "categories": [
                "PC"
            ],
            "windows": "",
            "linux": "",
            "macos": "",
            "other_download_links": []
        },
        {
            "name": "Saints Row 2",
            "categories": [
                "PC"
            ],
            "windows": "",
            "linux": "",
            "macos": "",
            "other_download_links": []
        },
        {
            "name": "Sniper Ghost Warrior Contracts",
            "categories": [
                "PC"
            ],
            "windows": "",
            "linux": "",
            "macos": "",
            "other_download_links": []
        },
        {
            "name": "Song of Horror: Complete Edition",
            "categories": [
                "PC"
            ],
            "windows": "",
            "linux": "",
            "macos": "",
            "other_download_links": []
        },
        {
            "name": "Source of Madness",
            "categories": [
                "PC"
            ],
            "windows": "",
            "linux": "",
            "macos": "",
            "other_download_links": []
        },
        {
            "name": "Sunwards",
            "categories": [
                "PC"
            ],
            "windows": "",
            "linux": "",
            "macos": "",
            "other_download_links": []
        },
        {
            "name": "T.M.N.T: Out of the Shadows",
            "categories": [
                "PC"
            ],
            "windows": "",
            "linux": "",
            "macos": "",
            "other_download_links": []
        },
        {
            "name": "The Evil Within 2",
            "categories": [
                "PC"
            ],
            "windows": "",
            "linux": "",
            "macos": "",
            "other_download_links": []
        },
        {
            "name": "The Godfather II",
            "categories": [
                "PC"
            ],
            "windows": "",
            "linux": "",
            "macos": "",
            "other_download_links": []
        },
        {
            "name": "The Godfather The Game",
            "categories": [
                "PC"
            ],
            "windows": "",
            "linux": "",
            "macos": "",
            "other_download_links": []
        },
        {
            "name": "Those Who Remain",
            "categories": [
                "PC"
            ],
            "windows": "",
            "linux": "",
            "macos": "",
            "other_download_links": []
        },
        {
            "name": "Thymesia",
            "categories": [
                "PC"
            ],
            "windows": "",
            "linux": "",
            "macos": "",
            "other_download_links": []
        },
        {
            "name": "Tower Hunter: Erza's Trial",
            "categories": [
                "PC"
            ],
            "windows": "",
            "linux": "",
            "macos": "",
            "other_download_links": []
        },
        {
            "name": "Trepang2",
            "categories": [
                "PC"
            ],
            "windows": "",
            "linux": "",
            "macos": "",
            "other_download_links": []
        },
        {
            "name": "Turok",
            "categories": [
                "PC"
            ],
            "windows": "",
            "linux": "",
            "macos": "",
            "other_download_links": []
        },
        {
            "name": "Warhammer 40,000: Space Marine A.E.",
            "categories": [
                "PC"
            ],
            "windows": "",
            "linux": "",
            "macos": "",
            "other_download_links": []
        },
        {
            "name": "Zorro The Chronicles",
            "categories": [
                "PC"
            ],
            "windows": "",
            "linux": "",
            "macos": "",
            "other_download_links": []
        }
    ]
}
